eulertools/__init__.py
eulertools/__main__.py
eulertools/__version__.py
eulertools/lib/__init__.py
eulertools/lib/constants.py
eulertools/lib/exceptions.py
eulertools/lib/parser.py
eulertools/lib/utils.py
eulertools/py.typed
eulertools/subcommands/__init__.py
eulertools/subcommands/compare.py
eulertools/subcommands/generate.py
eulertools/subcommands/run.py
eulertools/subcommands/statement.py
eulertools/subcommands/test.py
eulertools/subcommands/time.py
eulertools-5.3.0.dist-info/METADATA
eulertools-5.3.0.dist-info/WHEEL
eulertools-5.3.0.dist-info/entry_points.txt
eulertools-5.3.0.dist-info/RECORD
