Metadata-Version: 2.3
Name: eulertools
Version: 5.3.0
Summary: Multilanguage competitive coding toolbox
Home-page: https://eulertools.readthedocs.io/en/stable/
License: BSD-3-Clause
Keywords: leetcode,project_euler,topcoder
Author: Stephanos Kuma
Author-email: "Stephanos Kuma" <stephanos@kuma.ai>
Requires-Python: >=3.11
Classifier: Development Status :: 5 - Production/Stable
Classifier: License :: OSI Approved :: BSD License
Classifier: Operating System :: OS Independent
Classifier: Programming Language :: Python :: 3 :: Only
Requires-Dist: dj-settings (~=6.0)
Requires-Dist: jinja2 (~=3.1)
Requires-Dist: pyutilkit (~=0.4)
Requires-Dist: pyyaml (~=6.0)
Project-URL: Documentation, https://eulertools.readthedocs.io/en/stable/
Project-URL: Repository, https://github.com/spapanik/eulertools
